cs/result.py
cs_result-20250306.dist-info/WHEEL
cs_result-20250306.dist-info/METADATA
cs_result-20250306.dist-info/RECORD
