Metadata-Version: 2.4
Name: cs-result
Version: 20250306
Summary: Result and friends: various subclassable classes for deferred delivery of values.
Keywords: python2,python3
Author-email: Cameron Simpson <cs@cskk.id.au>
Classifier: Programming Language :: Python
Classifier: Programming Language :: Python :: 3
Classifier: Development Status :: 4 - Beta
Classifier: Intended Audience :: Developers
Classifier: Operating System :: OS Independent
Classifier: Topic :: Software Development :: Libraries :: Python Modules
Classifier: License :: OSI Approved :: GNU General Public License v3 or later (GPLv3+)
Requires-Dist: cs.deco>=20250306
Requires-Dist: cs.fsm>=20250120
Requires-Dist: cs.gimmicks>=20240316
Requires-Dist: cs.mappings>=20250306
Requires-Dist: cs.pfx>=20241208
Requires-Dist: cs.py.func>=20240630
Requires-Dist: cs.seq>=20250306
Requires-Dist: cs.threads>=20241005
Project-URL: MonoRepo Commits, https://bitbucket.org/cameron_simpson/css/commits/branch/main
Project-URL: Monorepo Git Mirror, https://github.com/cameron-simpson/css
Project-URL: Monorepo Hg/Mercurial Mirror, https://hg.sr.ht/~cameron-simpson/css
Project-URL: Source, https://github.com/cameron-simpson/css/blob/main/lib/python/cs/result.py
